chance_soya-0.0.3.dist-info/DESCRIPTION.rst
chance_soya-0.0.3.dist-info/METADATA
chance_soya-0.0.3.dist-info/RECORD
chance_soya-0.0.3.dist-info/WHEEL
chance_soya-0.0.3.dist-info/metadata.json
chance_soya-0.0.3.dist-info/top_level.txt
soya/__init__.py
soya/process.py
