Metadata-Version: 2.0
Name: chance-soya
Version: 0.0.3
Summary: The python project for calculating financial indexes
Home-page: https://github.com/chancefocus/soya
Author: Jimin Huang
Author-email: huangjimin@whu.edu.cn
License: MIT
Platform: UNKNOWN
Requires-Dist: arrow (>=0.7.0)
Requires-Dist: mock (>=2.0.0)
Requires-Dist: nose (>=1.3.7)
Requires-Dist: coverage (>=4.1)
Requires-Dist: Sphinx (>=1.6.5)
Requires-Dist: sphinx-rtd-theme (>=0.1.9chance-config>=0.0.4)
Requires-Dist: pandas (==0.22.0)
